<?xml version="1.0" encoding="UTF-8" standalone="yes"?>
<addon  id="plugin.video.plexkodiconnect"
        name="PlexKodiConnect" 
        version="1.6.1"
        provider-name="croneter">
  <requires>
    <import addon="xbmc.python" version="2.1.0"/>
    <import addon="script.module.requests" version="2.3.0" />
  </requires>
  <extension    point="xbmc.python.pluginsource"
                library="default.py">
        <provides>video audio image</provides>
  </extension>
  <extension point="xbmc.service" library="service.py" start="login">
  </extension>
  <extension point="kodi.context.item" library="contextmenu.py">
      <item>
        <label>30401</label>
              <description>30416</description>
              <visible>[!IsEmpty(ListItem.DBID) + !StringCompare(ListItem.DBID,-1) | !IsEmpty(ListItem.Property(plexid))] + !IsEmpty(Window(10000).Property(plex_context))</visible>
      </item>
  </extension>
  <extension point="xbmc.addon.metadata">
    <summary lang="en">Native Integration of Plex into Kodi</summary>
    <summary lang="en_gb">Native Integration of Plex into Kodi</summary>
    <summary lang="en_us">Native Integration of Plex into Kodi</summary>
    <summary lang="cs">Úplná integrace Plexu do Kodi</summary>
    <summary lang="de">Komplette Integration von Plex in Kodi</summary>
    <summary lang="es">Native Integration of Plex into Kodi</summary>
    <description lang="en">Connect Kodi to your Plex Media Server. This plugin assumes that you manage all your videos with Plex (and none with Kodi). You might lose data already stored in the Kodi video and music databases (as this plugin directly changes them). Use at your own risk!</description>
    <description lang="en_gb">Connect Kodi to your Plex Media Server. This plugin assumes that you manage all your videos with Plex (and none with Kodi). You might lose data already stored in the Kodi video and music databases (as this plugin directly changes them). Use at your own risk!</description>
    <description lang="en_us">Connect Kodi to your Plex Media Server. This plugin assumes that you manage all your videos with Plex (and none with Kodi). You might lose data already stored in the Kodi video and music databases (as this plugin directly changes them). Use at your own risk!</description>
    <description lang="cs">Připojte Kodi ke svému Plex Media Serveru. Tento doplněk předpokládá, že spravujete veškerá svá videa pomocí Plexu (nikoliv pomocí Kodi). Můžete přijít o data uložená ve video a hudební databázi Kodi (tento doplněk je přímo mění). Používejte na vlastní nebezpečí!</description>
    <description lang="de">Verbindet Kodi mit deinem Plex Media Server. Dieses Addon geht davon aus, dass du all deine Videos mit Plex verwaltest (und keine direkt mit Kodi). Du wirst möglicherweise Daten verlieren, die bereits in der Kodi Video- und/oder Musik-Datenbank gespeichert sind (da dieses Addon beide Datenbanken direkt verändert). Verwende auf eigene Gefahr!</description>
    <description lang="es">Connect Kodi to your Plex Media Server. This plugin assumes that you manage all your videos with Plex (and none with Kodi). You might lose data already stored in the Kodi video and music databases (as this plugin directly changes them). Use at your own risk!</description>
    <platform>all</platform>
    <license>GPL v2.0</license>
    <forum>https://forums.plex.tv</forum>
    <website>https://github.com/croneter/PlexKodiConnect</website>
    <email></email>
    <source>https://github.com/croneter/PlexKodiConnect</source>
  </extension>
</addon>